addok_getbyid/__init__.py
addok_getbyid-0.0.7.dist-info/LICENSE
addok_getbyid-0.0.7.dist-info/METADATA
addok_getbyid-0.0.7.dist-info/WHEEL
addok_getbyid-0.0.7.dist-info/entry_points.txt
addok_getbyid-0.0.7.dist-info/top_level.txt
addok_getbyid-0.0.7.dist-info/RECORD
